somenergia_dag_utils/__init__.py
somenergia_dag_utils/t_branch_pull_ssh.py
somenergia_dag_utils/t_check_repo.py
somenergia_dag_utils/t_git_clone_ssh.py
somenergia_dag_utils/t_image_build.py
somenergia_dag_utils/t_pre_prod_discriminator.py
somenergia_dag_utils/t_remove_image.py
somenergia_dag_utils/t_update_docker_image.py
somenergia_dag_utils-0.2.1.dist-info/LICENSE
somenergia_dag_utils-0.2.1.dist-info/METADATA
somenergia_dag_utils-0.2.1.dist-info/WHEEL
somenergia_dag_utils-0.2.1.dist-info/RECORD
